{
	"type": "minecraft:chest",
	"pools": [
		{
			"rolls": {
				"type": "minecraft:uniform",
				"min": 1,
				"max": 2
			},
			"bonus_rolls": {
				"min": 0,
				"max": 1
			},
			"entries": [
				{
					"type": "minecraft:item",
					"weight": 4,
					"quality": 1,
					"name": "minecraft:diamond",
					"functions": [
						{
							"function": "minecraft:set_count",
							"count": {
								"type": "minecraft:uniform",
								"min": 1,
								"max": 2
							},
							"add": false
						}
					]
				},
				{
					"type": "minecraft:item",
					"weight": 9,
					"quality": -1,
					"name": "minecraft:iron_ingot",
					"functions": [
						{
							"function": "minecraft:set_count",
							"count": {
								"type": "minecraft:uniform",
								"min": 2,
								"max": 3
							},
							"add": false
						}
					]
				},
				{
					"type": "minecraft:item",
					"weight": 9,
					"quality": 1,
					"name": "minecraft:gold_ingot",
					"functions": [
						{
							"function": "minecraft:set_count",
							"count": {
								"type": "minecraft:uniform",
								"min": 2,
								"max": 3
							},
							"add": false
						}
					]
				},
				{
					"type": "minecraft:item",
					"weight": 6,
					"quality": 1,
					"name": "minecraft:emerald",
					"functions": [
						{
							"function": "minecraft:set_count",
							"count": {
								"type": "minecraft:uniform",
								"min": 2,
								"max": 4
							},
							"add": false
						}
					]
				}
			]
		},
		{
			"rolls": 1,
			"entries": [
				{
					"type": "minecraft:loot_table",
					"name": "fokastudio:end/treasure_heads"
				}
			],
			"conditions": [
				{
					"condition": "minecraft:alternative",
					"terms": [
						{
							"condition": "minecraft:random_chance",
							"chance": 0.25
						}
					]
				}
			]
		},
		{
			"rolls": 1,
			"entries": [
				{
					"type": "minecraft:loot_table",
					"weight": 1,
					"name": "fokastudio:end/hallowed_armor"
				},
				{
					"type": "minecraft:loot_table",
					"weight": 1,
					"name": "fokastudio:end/ancient_armor"
				}
			],
			"conditions": [
				{
					"condition": "minecraft:alternative",
					"terms": [
						{
							"condition": "minecraft:random_chance",
							"chance": 0.66
						}
					]
				}
			]
		},
		{
			"rolls": {
				"min": 1,
				"max": 2
			},
			"entries": [
				{
					"type": "minecraft:item",
					"weight": 3,
					"name": "minecraft:diamond_sword"
				},
				{
					"type": "minecraft:item",
					"weight": 3,
					"name": "minecraft:diamond_boots"
				},
				{
					"type": "minecraft:item",
					"weight": 3,
					"name": "minecraft:diamond_chestplate"
				},
				{
					"type": "minecraft:item",
					"weight": 3,
					"name": "minecraft:diamond_leggings"
				},
				{
					"type": "minecraft:item",
					"weight": 3,
					"name": "minecraft:diamond_helmet"
				},
				{
					"type": "minecraft:item",
					"weight": 3,
					"name": "minecraft:diamond_pickaxe"
				},
				{
					"type": "minecraft:item",
					"weight": 3,
					"name": "minecraft:diamond_shovel"
				},
				{
					"type": "minecraft:item",
					"weight": 3,
					"name": "minecraft:diamond_hoe"
				},
				{
					"type": "minecraft:item",
					"weight": 3,
					"name": "minecraft:diamond_axe"
				},
				{
					"type": "minecraft:item",
					"name": "minecraft:diamond_horse_armor"
				}
			],
			"functions": [
				{
					"function": "minecraft:enchant_with_levels",
					"levels": {
						"type": "minecraft:uniform",
						"min": 15,
						"max": 30
					},
					"treasure": true
				},
				{
					"function": "minecraft:set_damage",
					"damage": {
						"min": 0.1,
						"max": 0.87
					},
					"add": false
				}
			]
		},
		{
			"rolls": {
				"min": 0,
				"max": 1
			},
			"entries": [
				{
					"type": "minecraft:item",
					"weight": 5,
					"quality": -1,
					"name": "minecraft:purpur_block",
					"functions": [
						{
							"function": "minecraft:set_count",
							"count": {
								"min": 3,
								"max": 6
							},
							"add": false
						}
					]
				},
				{
					"type": "minecraft:item",
					"weight": 5,
					"quality": -1,
					"name": "minecraft:end_stone",
					"functions": [
						{
							"function": "minecraft:set_count",
							"count": {
								"min": 3,
								"max": 6
							},
							"add": false
						}
					]
				},
				{
					"type": "minecraft:item",
					"weight": 2,
					"name": "minecraft:crying_obsidian",
					"functions": [
						{
							"function": "minecraft:set_count",
							"count": {
								"min": 2,
								"max": 4
							},
							"add": false
						}
					]
				}
			]
		},
		{
			"rolls": {
				"min": 1,
				"max": 2
			},
			"entries": [
				{
					"type": "minecraft:item",
					"weight": 3,
					"quality": -1,
					"name": "minecraft:ender_pearl",
					"functions": [
						{
							"function": "minecraft:set_count",
							"count": {
								"min": 3,
								"max": 4
							},
							"add": false
						}
					]
				},
				{
					"type": "minecraft:item",
					"name": "minecraft:firework_rocket",
					"functions": [
						{
							"function": "minecraft:set_count",
							"count": {
								"min": 1,
								"max": 4
							},
							"add": false
						}
					]
				},
				{
					"type": "minecraft:item",
					"weight": 3,
					"quality": -1,
					"name": "minecraft:amethyst_shard",
					"functions": [
						{
							"function": "minecraft:set_count",
							"count": {
								"min": 1,
								"max": 2
							},
							"add": false
						}
					]
				},
				{
					"type": "minecraft:item",
					"name": "minecraft:shulker_shell",
					"functions": [
						{
							"function": "minecraft:set_count",
							"count": {
								"min": 1,
								"max": 2
							},
							"add": false
						}
					]
				},
				{
					"type": "minecraft:item",
					"weight": 3,
					"name": "minecraft:phantom_membrane",
					"functions": [
						{
							"function": "minecraft:set_count",
							"count": {
								"min": 1,
								"max": 2
							},
							"add": false
						}
					]
				},
				{
					"type": "minecraft:item",
					"weight": 4,
					"quality": -1,
					"name": "minecraft:chorus_fruit",
					"functions": [
						{
							"function": "minecraft:set_count",
							"count": {
								"min": 1,
								"max": 2
							},
							"add": false
						}
					]
				},
				{
					"type": "minecraft:loot_table",
					"quality": 2,
					"name": "fokastudio:end/items/golden_chorus_fruit"
				}
			]
		}
	]
}
